scify_file_reader/__init__.py
scify_file_reader/file_reader.py
scify_file_reader-0.0.2.dist-info/METADATA
scify_file_reader-0.0.2.dist-info/WHEEL
scify_file_reader-0.0.2.dist-info/top_level.txt
scify_file_reader-0.0.2.dist-info/RECORD
