Metadata-Version: 2.1
Name: scify-file-reader
Version: 0.0.2
Summary: A class to handle and process multiple files with identical structures within a directory.
Home-page: https://github.com/Jeferson-Peter/scify-file-reader
Author: Jeferson-Peter (Jeferson Peter)
Author-email: jeferson.peter@pm.me
Keywords: Python,File Reading,Multiple File Handler
Classifier: Development Status :: 1 - Planning
Classifier: Intended Audience :: Developers
Classifier: Programming Language :: Python :: 3.10
Classifier: Programming Language :: Python :: 3.11
Classifier: Operating System :: Unix
Classifier: Operating System :: MacOS :: MacOS X
Classifier: Operating System :: Microsoft :: Windows
Requires-Dist: pandas (>=1.5.3)
Requires-Dist: pyarrow
